pyEVT/EvtExchanger.py
pyEVT/__init__.py
pyEVT-0.99.31.dist-info/LICENCE
pyEVT-0.99.31.dist-info/METADATA
pyEVT-0.99.31.dist-info/WHEEL
pyEVT-0.99.31.dist-info/top_level.txt
pyEVT-0.99.31.dist-info/RECORD
