Metadata-Version: 2.1
Name: pyEVT
Version: 0.99.31
Summary: Package to communicate with RUG developed hardware
Home-page: https://github.com/markspan/pyEVT
Author: Eise Hoekstra and Mark Span (primary developer)
Author-email: m.m.span@rug.nl
License: UNKNOWN
Download-URL: https://github.com/markspan/pyEVT/dist/pyEVT-0.99.31.tar.gz
Platform: UNKNOWN
Classifier: Programming Language :: Python :: 3
Classifier: License :: OSI Approved :: MIT License
Classifier: Operating System :: OS Independent
Classifier: Intended Audience :: Science/Research
Requires-Python: >=3.6
License-File: LICENCE
Requires-Dist: hidapi
